videocondenser.py
videocondenser-0.2.dist-info/LICENSE.txt
videocondenser-0.2.dist-info/METADATA
videocondenser-0.2.dist-info/WHEEL
videocondenser-0.2.dist-info/entry_points.txt
videocondenser-0.2.dist-info/RECORD
