Metadata-Version: 2.1
Name: videocondenser
Version: 0.2
Summary: A tool that condenses videos by adjusting playback speed based on volume.
License: GPL-3.0-or-later
Author: Frank Sacco
Author-email: franka25sacco@gmail.com
Requires-Python: >=3.11,<4.0
Classifier: License :: OSI Approved :: GNU General Public License v3 or later (GPLv3+)
Classifier: Programming Language :: Python :: 3
Classifier: Programming Language :: Python :: 3.11
Project-URL: Repository, https://github.com/frank-monkey/videocondenser
